itacate.py
itacate-1.0.3.dist-info/DESCRIPTION.rst
itacate-1.0.3.dist-info/LICENSE.txt
itacate-1.0.3.dist-info/METADATA
itacate-1.0.3.dist-info/RECORD
itacate-1.0.3.dist-info/WHEEL
itacate-1.0.3.dist-info/metadata.json
itacate-1.0.3.dist-info/top_level.txt
